[
  {
    "login": "kjkuan",
    "id": 973329,
    "avatar_url": "https://avatars3.githubusercontent.com/u/973329?v=3",
    "gravatar_id": "",
    "url": "",
    "html_url": "",
    "followers_url": "https://api.github.com/users/kjkuan/followers",
    "following_url": "https://api.github.com/users/kjkuan/following{/other_user}",
    "gists_url": "https://api.github.com/users/kjkuan/gists{/gist_id}",
    "starred_url": "https://api.github.com/users/kjkuan/starred{/owner}{/repo}",
    "subscriptions_url": "https://api.github.com/users/kjkuan/subscriptions",
    "organizations_url": "https://api.github.com/users/kjkuan/orgs",
    "repos_url": "https://api.github.com/users/kjkuan/repos",
    "events_url": "https://api.github.com/users/kjkuan/events{/privacy}",
    "received_events_url": "https://api.github.com/users/kjkuan/received_events",
    "type": "User",
    "site_admin": false,
    "contributions": 88
  },
  {
    "login": "thedrow",
    "id": 48936,
    "avatar_url": "https://avatars1.githubusercontent.com/u/48936?v=3",
    "gravatar_id": "",
    "url": "https://api.github.com/users/thedrow",
    "html_url": "",
    "followers_url": "https://api.github.com/users/thedrow/followers",
    "following_url": "https://api.github.com/users/thedrow/following{/other_user}",
    "gists_url": "https://api.github.com/users/thedrow/gists{/gist_id}",
    "starred_url": "https://api.github.com/users/thedrow/starred{/owner}{/repo}",
    "subscriptions_url": "https://api.github.com/users/thedrow/subscriptions",
    "organizations_url": "https://api.github.com/users/thedrow/orgs",
    "repos_url": "https://api.github.com/users/thedrow/repos",
    "events_url": "https://api.github.com/users/thedrow/events{/privacy}",
    "received_events_url": "https://api.github.com/users/thedrow/received_events",
    "type": "User",
    "site_admin": false,
    "contributions": 86
  },
  {
    "login": "alexbleotu",
    "id": 17009281,
    "avatar_url": "https://avatars0.githubusercontent.com/u/17009281?v=3",
    "gravatar_id": "",
    "url": "https://api.github.com/users/alexbleotu",
    "html_url": "https://github.com/alexbleotu",
    "followers_url": "https://api.github.com/users/alexbleotu/followers",
    "following_url": "https://api.github.com/users/alexbleotu/following{/other_user}",
    "gists_url": "https://api.github.com/users/alexbleotu/gists{/gist_id}",
    "starred_url": "https://api.github.com/users/alexbleotu/starred{/owner}{/repo}",
    "subscriptions_url": "https://api.github.com/users/alexbleotu/subscriptions",
    "organizations_url": "https://api.github.com/users/alexbleotu/orgs",
    "repos_url": "https://api.github.com/users/alexbleotu/repos",
    "events_url": "https://api.github.com/users/alexbleotu/events{/privacy}",
    "received_events_url": "https://api.github.com/users/alexbleotu/received_events",
    "type": "User",
    "site_admin": false,
    "contributions": 85
  },
  {
    "login": "bdrung",
    "id": 239485,
    "avatar_url": "https://avatars1.githubusercontent.com/u/239485?v=3",
    "gravatar_id": "",
    "url": "https://api.github.com/users/bdrung",
    "html_url": "https://github.com/bdrung",
    "followers_url": "https://api.github.com/users/bdrung/followers",
    "following_url": "https://api.github.com/users/bdrung/following{/other_user}",
    "gists_url": "https://api.github.com/users/bdrung/gists{/gist_id}",
    "starred_url": "https://api.github.com/users/bdrung/starred{/owner}{/repo}",
    "subscriptions_url": "https://api.github.com/users/bdrung/subscriptions",
    "organizations_url": "https://api.github.com/users/bdrung/orgs",
    "repos_url": "https://api.github.com/users/bdrung/repos",
    "events_url": "https://api.github.com/users/bdrung/events{/privacy}",
    "received_events_url": "https://api.github.com/users/bdrung/received_events",
    "type": "User",
    "site_admin": false,
    "contributions": 85
  },
  {
    "login": "robertkeizer",
    "id": 339303,
    "avatar_url": "https://avatars0.githubusercontent.com/u/339303?v=3",
    "gravatar_id": "",
    "url": "https://api.github.com/users/robertkeizer",
    "html_url": "https://github.com/robertkeizer",
    "followers_url": "https://api.github.com/users/robertkeizer/followers",
    "following_url": "https://api.github.com/users/robertkeizer/following{/other_user}",
    "gists_url": "https://api.github.com/users/robertkeizer/gists{/gist_id}",
    "starred_url": "https://api.github.com/users/robertkeizer/starred{/owner}{/repo}",
    "subscriptions_url": "https://api.github.com/users/robertkeizer/subscriptions",
    "organizations_url": "https://api.github.com/users/robertkeizer/orgs",
    "repos_url": "https://api.github.com/users/robertkeizer/repos",
    "events_url": "https://api.github.com/users/robertkeizer/events{/privacy}",
    "received_events_url": "https://api.github.com/users/robertkeizer/received_events",
    "type": "User",
    "site_admin": false,
    "contributions": 85
  },
  {
    "login": "hvnsweeting",
    "id": 1000665,
    "avatar_url": "https://avatars3.githubusercontent.com/u/1000665?v=3",
    "gravatar_id": "",
    "url": "https://api.github.com/users/hvnsweeting",
    "followers_url": "https://api.github.com/users/hvnsweeting/followers",
    "following_url": "https://api.github.com/users/hvnsweeting/following{/other_user}",
    "gists_url": "https://api.github.com/users/hvnsweeting/gists{/gist_id}",
    "starred_url": "https://api.github.com/users/hvnsweeting/starred{/owner}{/repo}",
    "subscriptions_url": "https://api.github.com/users/hvnsweeting/subscriptions",
    "organizations_url": "https://api.github.com/users/hvnsweeting/orgs",
    "repos_url": "https://api.github.com/users/hvnsweeting/repos",
    "events_url": "https://api.github.com/users/hvnsweeting/events{/privacy}",
    "received_events_url": "https://api.github.com/users/hvnsweeting/received_events",
    "type": "User",
    "site_admin": false,
    "contributions": 83
  },
  {
    "login": "jhutchins",
    "id": 1349982,
    "avatar_url": "https://avatars2.githubusercontent.com/u/1349982?v=3",
    "gravatar_id": "",
    "url": "https://api.github.com/users/jhutchins",
    "html_url": "https://github.com/jhutchins",
    "followers_url": "https://api.github.com/users/jhutchins/followers",
    "following_url": "https://api.github.com/users/jhutchins/following{/other_user}",
    "gists_url": "https://api.github.com/users/jhutchins/gists{/gist_id}",
    "starred_url": "https://api.github.com/users/jhutchins/starred{/owner}{/repo}",
    "subscriptions_url": "https://api.github.com/users/jhutchins/subscriptions",
    "organizations_url": "https://api.github.com/users/jhutchins/orgs",
    "repos_url": "https://api.github.com/users/jhutchins/repos",
    "events_url": "https://api.github.com/users/jhutchins/events{/privacy}",
    "received_events_url": "https://api.github.com/users/jhutchins/received_events",
    "type": "User",
    "site_admin": false,
    "contributions": 79
  },
  {
    "login": "giantlock",
    "id": 1686427,
    "avatar_url": "https://avatars0.githubusercontent.com/u/1686427?v=3",
    "gravatar_id": "",
    "url": "https://api.github.com/users/giantlock",
    "html_url": "https://github.com/giantlock",
    "followers_url": "https://api.github.com/users/giantlock/followers",
    "following_url": "https://api.github.com/users/giantlock/following{/other_user}",
    "gists_url": "https://api.github.com/users/giantlock/gists{/gist_id}",
    "starred_url": "https://api.github.com/users/giantlock/starred{/owner}{/repo}",
    "subscriptions_url": "https://api.github.com/users/giantlock/subscriptions",
    "organizations_url": "https://api.github.com/users/giantlock/orgs",
    "repos_url": "https://api.github.com/users/giantlock/repos",
    "events_url": "https://api.github.com/users/giantlock/events{/privacy}",
    "received_events_url": "https://api.github.com/users/giantlock/received_events",
    "type": "User",
    "site_admin": false,
    "contributions": 77
  },
  {
    "login": "aboe76",
    "id": 1800660,
    "avatar_url": "https://avatars3.githubusercontent.com/u/1800660?v=3",
    "gravatar_id": "",
    "url": "https://api.github.com/users/aboe76",
    "html_url": "https://github.com/aboe76",
    "followers_url": "https://api.github.com/users/aboe76/followers",
    "following_url": "https://api.github.com/users/aboe76/following{/other_user}",
    "gists_url": "https://api.github.com/users/aboe76/gists{/gist_id}",
    "starred_url": "https://api.github.com/users/aboe76/starred{/owner}{/repo}",
    "subscriptions_url": "https://api.github.com/users/aboe76/subscriptions",
    "organizations_url": "https://api.github.com/users/aboe76/orgs",
    "repos_url": "https://api.github.com/users/aboe76/repos",
    "events_url": "https://api.github.com/users/aboe76/events{/privacy}",
    "received_events_url": "https://api.github.com/users/aboe76/received_events",
    "type": "User",
    "site_admin": false,
    "contributions": 76
  },
  {
    "login": "multani",
    "id": 65311,
    "avatar_url": "https://avatars3.githubusercontent.com/u/65311?v=3",
    "gravatar_id": "",
    "url": "https://api.github.com/users/multani",
    "html_url": "https://github.com/multani",
    "followers_url": "https://api.github.com/users/multani/followers",
    "following_url": "https://api.github.com/users/multani/following{/other_user}",
    "gists_url": "https://api.github.com/users/multani/gists{/gist_id}",
    "starred_url": "https://api.github.com/users/multani/starred{/owner}{/repo}",
    "subscriptions_url": "https://api.github.com/users/multani/subscriptions",
    "organizations_url": "https://api.github.com/users/multani/orgs",
    "repos_url": "https://api.github.com/users/multani/repos",
    "events_url": "https://api.github.com/users/multani/events{/privacy}",
    "received_events_url": "https://api.github.com/users/multani/received_events",
    "type": "User",
    "site_admin": false,
    "contributions": 76
  },
  {
    "login": "herlo",
    "id": 89334,
    "avatar_url": "https://avatars1.githubusercontent.com/u/89334?v=3",
    "gravatar_id": "",
    "url": "https://api.github.com/users/herlo",
    "html_url": "https://github.com/herlo",
    "followers_url": "https://api.github.com/users/herlo/followers",
    "following_url": "https://api.github.com/users/herlo/following{/other_user}",
    "gists_url": "https://api.github.com/users/herlo/gists{/gist_id}",
    "starred_url": "https://api.github.com/users/herlo/starred{/owner}{/repo}",
    "subscriptions_url": "https://api.github.com/users/herlo/subscriptions",
    "organizations_url": "https://api.github.com/users/herlo/orgs",
    "repos_url": "https://api.github.com/users/herlo/repos",
    "events_url": "https://api.github.com/users/herlo/events{/privacy}",
    "received_events_url": "https://api.github.com/users/herlo/received_events",
    "type": "User",
    "site_admin": false,
    "contributions": 75
  },
  {
    "login": "0xf10e",
    "id": 6215293,
    "avatar_url": "https://avatars0.githubusercontent.com/u/6215293?v=3",
    "gravatar_id": "",
    "url": "https://api.github.com/users/0xf10e",
    "html_url": "https://github.com/0xf10e",
    "followers_url": "https://api.github.com/users/0xf10e/followers",
    "following_url": "https://api.github.com/users/0xf10e/following{/other_user}",
    "gists_url": "https://api.github.com/users/0xf10e/gists{/gist_id}",
    "starred_url": "https://api.github.com/users/0xf10e/starred{/owner}{/repo}",
    "subscriptions_url": "https://api.github.com/users/0xf10e/subscriptions",
    "organizations_url": "https://api.github.com/users/0xf10e/orgs",
    "repos_url": "https://api.github.com/users/0xf10e/repos",
    "events_url": "https://api.github.com/users/0xf10e/events{/privacy}",
    "received_events_url": "https://api.github.com/users/0xf10e/received_events",
    "type": "User",
    "site_admin": false,
    "contributions": 74
  },
  {
    "login": "lorengordon",
    "id": 8457307,
    "avatar_url": "https://avatars0.githubusercontent.com/u/8457307?v=3",
    "gravatar_id": "",
    "url": "https://api.github.com/users/lorengordon",
    "html_url": "https://github.com/lorengordon",
    "followers_url": "https://api.github.com/users/lorengordon/followers",
    "following_url": "https://api.github.com/users/lorengordon/following{/other_user}",
    "gists_url": "https://api.github.com/users/lorengordon/gists{/gist_id}",
    "starred_url": "https://api.github.com/users/lorengordon/starred{/owner}{/repo}",
    "subscriptions_url": "https://api.github.com/users/lorengordon/subscriptions",
    "organizations_url": "https://api.github.com/users/lorengordon/orgs",
    "repos_url": "https://api.github.com/users/lorengordon/repos",
    "events_url": "https://api.github.com/users/lorengordon/events{/privacy}",
    "received_events_url": "https://api.github.com/users/lorengordon/received_events",
    "type": "User",
    "site_admin": false,
    "contributions": 73
  },
  {
    "login": "ranl",
    "id": 869615,
    "avatar_url": "https://avatars2.githubusercontent.com/u/869615?v=3",
    "gravatar_id": "",
    "url": "https://api.github.com/users/ranl",
    "html_url": "https://github.com/ranl",
    "followers_url": "https://api.github.com/users/ranl/followers",
    "following_url": "https://api.github.com/users/ranl/following{/other_user}",
    "gists_url": "https://api.github.com/users/ranl/gists{/gist_id}",
    "starred_url": "https://api.github.com/users/ranl/starred{/owner}{/repo}",
    "subscriptions_url": "https://api.github.com/users/ranl/subscriptions",
    "organizations_url": "https://api.github.com/users/ranl/orgs",
    "repos_url": "https://api.github.com/users/ranl/repos",
    "events_url": "https://api.github.com/users/ranl/events{/privacy}",
    "received_events_url": "https://api.github.com/users/ranl/received_events",
    "type": "User",
    "site_admin": false,
    "contributions": 72
  },
  {
    "login": "evinrude",
    "id": 1393481,
    "avatar_url": "https://avatars1.githubusercontent.com/u/1393481?v=3",
    "gravatar_id": "",
    "url": "https://api.github.com/users/evinrude",
    "html_url": "https://github.com/evinrude",
    "followers_url": "https://api.github.com/users/evinrude/followers",
    "following_url": "https://api.github.com/users/evinrude/following{/other_user}",
    "gists_url": "https://api.github.com/users/evinrude/gists{/gist_id}",
    "starred_url": "https://api.github.com/users/evinrude/starred{/owner}{/repo}",
    "subscriptions_url": "https://api.github.com/users/evinrude/subscriptions",
    "organizations_url": "https://api.github.com/users/evinrude/orgs",
    "repos_url": "https://api.github.com/users/evinrude/repos",
    "events_url": "https://api.github.com/users/evinrude/events{/privacy}",
    "received_events_url": "https://api.github.com/users/evinrude/received_events",
    "type": "User",
    "site_admin": false,
    "contributions": 71
  },
  {
    "login": "baijum",
    "id": 121129,
    "avatar_url": "https://avatars0.githubusercontent.com/u/121129?v=3",
    "gravatar_id": "",
    "url": "https://api.github.com/users/baijum",
    "html_url": "https://github.com/baijum",
    "followers_url": "https://api.github.com/users/baijum/followers",
    "following_url": "https://api.github.com/users/baijum/following{/other_user}",
    "gists_url": "https://api.github.com/users/baijum/gists{/gist_id}",
    "starred_url": "https://api.github.com/users/baijum/starred{/owner}{/repo}",
    "subscriptions_url": "https://api.github.com/users/baijum/subscriptions",
    "organizations_url": "https://api.github.com/users/baijum/orgs",
    "repos_url": "https://api.github.com/users/baijum/repos",
    "events_url": "https://api.github.com/users/baijum/events{/privacy}",
    "received_events_url": "https://api.github.com/users/baijum/received_events",
    "type": "User",
    "site_admin": false,
    "contributions": 69
  },
  {
    "login": "cedwards",
    "id": 534685,
    "avatar_url": "https://avatars0.githubusercontent.com/u/534685?v=3",
    "gravatar_id": "",
    "url": "https://api.github.com/users/cedwards",
    "html_url": "https://github.com/cedwards",
    "followers_url": "https://api.github.com/users/cedwards/followers",
    "following_url": "https://api.github.com/users/cedwards/following{/other_user}",
    "gists_url": "https://api.github.com/users/cedwards/gists{/gist_id}",
    "starred_url": "https://api.github.com/users/cedwards/starred{/owner}{/repo}",
    "subscriptions_url": "https://api.github.com/users/cedwards/subscriptions",
    "organizations_url": "https://api.github.com/users/cedwards/orgs",
    "repos_url": "https://api.github.com/users/cedwards/repos",
    "events_url": "https://api.github.com/users/cedwards/events{/privacy}",
    "received_events_url": "https://api.github.com/users/cedwards/received_events",
    "type": "User",
    "site_admin": false,
    "contributions": 69
  },
  {
    "login": "syphernl",
    "id": 639906,
    "avatar_url": "https://avatars2.githubusercontent.com/u/639906?v=3",
    "gravatar_id": "",
    "url": "https://api.github.com/users/syphernl",
    "html_url": "https://github.com/syphernl",
    "followers_url": "https://api.github.com/users/syphernl/followers",
    "following_url": "https://api.github.com/users/syphernl/following{/other_user}",
    "gists_url": "https://api.github.com/users/syphernl/gists{/gist_id}",
    "starred_url": "https://api.github.com/users/syphernl/starred{/owner}{/repo}",
    "subscriptions_url": "https://api.github.com/users/syphernl/subscriptions",
    "organizations_url": "https://api.github.com/users/syphernl/orgs",
    "repos_url": "https://api.github.com/users/syphernl/repos",
    "events_url": "https://api.github.com/users/syphernl/events{/privacy}",
    "received_events_url": "https://api.github.com/users/syphernl/received_events",
    "type": "User",
    "site_admin": false,
    "contributions": 65
  },
  {
    "login": "bbinet",
    "id": 76281,
    "avatar_url": "https://avatars3.githubusercontent.com/u/76281?v=3",
    "gravatar_id": "",
    "url": "https://api.github.com/users/bbinet",
    "html_url": "https://github.com/bbinet",
    "followers_url": "https://api.github.com/users/bbinet/followers",
    "following_url": "https://api.github.com/users/bbinet/following{/other_user}",
    "gists_url": "https://api.github.com/users/bbinet/gists{/gist_id}",
    "starred_url": "https://api.github.com/users/bbinet/starred{/owner}{/repo}",
    "subscriptions_url": "https://api.github.com/users/bbinet/subscriptions",
    "organizations_url": "https://api.github.com/users/bbinet/orgs",
    "repos_url": "https://api.github.com/users/bbinet/repos",
    "events_url": "https://api.github.com/users/bbinet/events{/privacy}",
    "received_events_url": "https://api.github.com/users/bbinet/received_events",
    "type": "User",
    "site_admin": false,
    "contributions": 64
  },
  {
    "login": "m03",
    "id": 3432358,
    "avatar_url": "https://avatars0.githubusercontent.com/u/3432358?v=3",
    "gravatar_id": "",
    "url": "https://api.github.com/users/m03",
    "html_url": "https://github.com/m03",
    "followers_url": "https://api.github.com/users/m03/followers",
    "following_url": "https://api.github.com/users/m03/following{/other_user}",
    "gists_url": "https://api.github.com/users/m03/gists{/gist_id}",
    "starred_url": "https://api.github.com/users/m03/starred{/owner}{/repo}",
    "subscriptions_url": "https://api.github.com/users/m03/subscriptions",
    "organizations_url": "https://api.github.com/users/m03/orgs",
    "repos_url": "https://api.github.com/users/m03/repos",
    "events_url": "https://api.github.com/users/m03/events{/privacy}",
    "received_events_url": "https://api.github.com/users/m03/received_events",
    "type": "User",
    "site_admin": false,
    "contributions": 61
  },
  {
    "login": "kaithar",
    "id": 76736,
    "avatar_url": "https://avatars3.githubusercontent.com/u/76736?v=3",
    "gravatar_id": "",
    "url": "https://api.github.com/users/kaithar",
    "html_url": "https://github.com/kaithar",
    "followers_url": "https://api.github.com/users/kaithar/followers",
    "following_url": "https://api.github.com/users/kaithar/following{/other_user}",
    "gists_url": "https://api.github.com/users/kaithar/gists{/gist_id}",
    "starred_url": "https://api.github.com/users/kaithar/starred{/owner}{/repo}",
    "subscriptions_url": "https://api.github.com/users/kaithar/subscriptions",
    "organizations_url": "https://api.github.com/users/kaithar/orgs",
    "repos_url": "https://api.github.com/users/kaithar/repos",
    "events_url": "https://api.github.com/users/kaithar/events{/privacy}",
    "received_events_url": "https://api.github.com/users/kaithar/received_events",
    "type": "User",
    "site_admin": false,
    "contributions": 60
  },
  {
    "login": "MTecknology",
    "id": 1413430,
    "avatar_url": "https://avatars3.githubusercontent.com/u/1413430?v=3",
    "gravatar_id": "",
    "url": "https://api.github.com/users/MTecknology",
    "html_url": "https://github.com/MTecknology",
    "followers_url": "https://api.github.com/users/MTecknology/followers",
    "following_url": "https://api.github.com/users/MTecknology/following{/other_user}",
    "gists_url": "https://api.github.com/users/MTecknology/gists{/gist_id}",
    "starred_url": "https://api.github.com/users/MTecknology/starred{/owner}{/repo}",
    "subscriptions_url": "https://api.github.com/users/MTecknology/subscriptions",
    "organizations_url": "https://api.github.com/users/MTecknology/orgs",
    "repos_url": "https://api.github.com/users/MTecknology/repos",
    "events_url": "https://api.github.com/users/MTecknology/events{/privacy}",
    "received_events_url": "https://api.github.com/users/MTecknology/received_events",
    "type": "User",
    "site_admin": false,
    "contributions": 59
  },
  {
    "login": "rominf",
    "id": 3449635,
    "avatar_url": "https://avatars0.githubusercontent.com/u/3449635?v=3",
    "gravatar_id": "",
    "url": "https://api.github.com/users/rominf",
    "html_url": "https://github.com/rominf",
    "followers_url": "https://api.github.com/users/rominf/followers",
    "following_url": "https://api.github.com/users/rominf/following{/other_user}",
    "gists_url": "https://api.github.com/users/rominf/gists{/gist_id}",
    "starred_url": "https://api.github.com/users/rominf/starred{/owner}{/repo}",
    "subscriptions_url": "https://api.github.com/users/rominf/subscriptions",
    "organizations_url": "https://api.github.com/users/rominf/orgs",
    "repos_url": "https://api.github.com/users/rominf/repos",
    "events_url": "https://api.github.com/users/rominf/events{/privacy}",
    "received_events_url": "https://api.github.com/users/rominf/received_events",
    "type": "User",
    "site_admin": false,
    "contributions": 59
  },
  {
    "login": "akissa",
    "id": 344251,
    "avatar_url": "https://avatars3.githubusercontent.com/u/344251?v=3",
    "gravatar_id": "",
    "url": "https://api.github.com/users/akissa",
    "html_url": "https://github.com/akissa",
    "followers_url": "https://api.github.com/users/akissa/followers",
    "following_url": "https://api.github.com/users/akissa/following{/other_user}",
    "gists_url": "https://api.github.com/users/akissa/gists{/gist_id}",
    "starred_url": "https://api.github.com/users/akissa/starred{/owner}{/repo}",
    "subscriptions_url": "https://api.github.com/users/akissa/subscriptions",
    "organizations_url": "https://api.github.com/users/akissa/orgs",
    "repos_url": "https://api.github.com/users/akissa/repos",
    "events_url": "https://api.github.com/users/akissa/events{/privacy}",
    "received_events_url": "https://api.github.com/users/akissa/received_events",
    "type": "User",
    "site_admin": false,
    "contributions": 58
  },
  {
    "login": "claudiupopescu",
    "id": 10415709,
    "avatar_url": "https://avatars2.githubusercontent.com/u/10415709?v=3",
    "gravatar_id": "",
    "url": "https://api.github.com/users/claudiupopescu",
    "html_url": "https://github.com/claudiupopescu",
    "followers_url": "https://api.github.com/users/claudiupopescu/followers",
    "following_url": "https://api.github.com/users/claudiupopescu/following{/other_user}",
    "gists_url": "https://api.github.com/users/claudiupopescu/gists{/gist_id}",
    "starred_url": "https://api.github.com/users/claudiupopescu/starred{/owner}{/repo}",
    "subscriptions_url": "https://api.github.com/users/claudiupopescu/subscriptions",
    "organizations_url": "https://api.github.com/users/claudiupopescu/orgs",
    "repos_url": "https://api.github.com/users/claudiupopescu/repos",
    "events_url": "https://api.github.com/users/claudiupopescu/events{/privacy}",
    "received_events_url": "https://api.github.com/users/claudiupopescu/received_events",
    "type": "User",
    "site_admin": false,
    "contributions": 58
  },
  {
    "login": "jodv",
    "id": 2186037,
    "avatar_url": "https://avatars2.githubusercontent.com/u/2186037?v=3",
    "gravatar_id": "",
    "url": "https://api.github.com/users/jodv",
    "html_url": "https://github.com/jodv",
    "followers_url": "https://api.github.com/users/jodv/followers",
    "following_url": "https://api.github.com/users/jodv/following{/other_user}",
    "gists_url": "https://api.github.com/users/jodv/gists{/gist_id}",
    "starred_url": "https://api.github.com/users/jodv/starred{/owner}{/repo}",
    "subscriptions_url": "https://api.github.com/users/jodv/subscriptions",
    "organizations_url": "https://api.github.com/users/jodv/orgs",
    "repos_url": "https://api.github.com/users/jodv/repos",
    "events_url": "https://api.github.com/users/jodv/events{/privacy}",
    "received_events_url": "https://api.github.com/users/jodv/received_events",
    "type": "User",
    "site_admin": false,
    "contributions": 57
  },
  {
    "login": "inthecloud247",
    "id": 1683995,
    "avatar_url": "https://avatars3.githubusercontent.com/u/1683995?v=3",
    "gravatar_id": "",
    "url": "https://api.github.com/users/inthecloud247",
    "html_url": "https://github.com/inthecloud247",
    "followers_url": "https://api.github.com/users/inthecloud247/followers",
    "following_url": "https://api.github.com/users/inthecloud247/following{/other_user}",
    "gists_url": "https://api.github.com/users/inthecloud247/gists{/gist_id}",
    "starred_url": "https://api.github.com/users/inthecloud247/starred{/owner}{/repo}",
    "subscriptions_url": "https://api.github.com/users/inthecloud247/subscriptions",
    "organizations_url": "https://api.github.com/users/inthecloud247/orgs",
    "repos_url": "https://api.github.com/users/inthecloud247/repos",
    "events_url": "https://api.github.com/users/inthecloud247/events{/privacy}",
    "received_events_url": "https://api.github.com/users/inthecloud247/received_events",
    "type": "User",
    "site_admin": false,
    "contributions": 57
  },
  {
    "login": "castor-morveer",
    "id": 16143452,
    "avatar_url": "https://avatars2.githubusercontent.com/u/16143452?v=3",
    "gravatar_id": "",
    "url": "https://api.github.com/users/castor-morveer",
    "html_url": "https://github.com/castor-morveer",
    "followers_url": "https://api.github.com/users/castor-morveer/followers",
    "following_url": "https://api.github.com/users/castor-morveer/following{/other_user}",
    "gists_url": "https://api.github.com/users/castor-morveer/gists{/gist_id}",
    "starred_url": "https://api.github.com/users/castor-morveer/starred{/owner}{/repo}",
    "subscriptions_url": "https://api.github.com/users/castor-morveer/subscriptions",
    "organizations_url": "https://api.github.com/users/castor-morveer/orgs",
    "repos_url": "https://api.github.com/users/castor-morveer/repos",
    "events_url": "https://api.github.com/users/castor-morveer/events{/privacy}",
    "received_events_url": "https://api.github.com/users/castor-morveer/received_events",
    "type": "User",
    "site_admin": false,
    "contributions": 56
  },
  {
    "login": "fxdgear",
    "id": 146550,
    "avatar_url": "https://avatars1.githubusercontent.com/u/146550?v=3",
    "gravatar_id": "",
    "url": "https://api.github.com/users/fxdgear",
    "html_url": "https://github.com/fxdgear",
    "followers_url": "https://api.github.com/users/fxdgear/followers",
    "following_url": "https://api.github.com/users/fxdgear/following{/other_user}",
    "gists_url": "https://api.github.com/users/fxdgear/gists{/gist_id}",
    "starred_url": "https://api.github.com/users/fxdgear/starred{/owner}{/repo}",
    "subscriptions_url": "https://api.github.com/users/fxdgear/subscriptions",
    "organizations_url": "https://api.github.com/users/fxdgear/orgs",
    "repos_url": "https://api.github.com/users/fxdgear/repos",
    "events_url": "https://api.github.com/users/fxdgear/events{/privacy}",
    "received_events_url": "https://api.github.com/users/fxdgear/received_events",
    "type": "User",
    "site_admin": false,
    "contributions": 54
  },
  {
    "login": "markusgattol",
    "id": 649821,
    "avatar_url": "https://avatars0.githubusercontent.com/u/649821?v=3",
    "gravatar_id": "",
    "url": "https://api.github.com/users/markusgattol",
    "html_url": "https://github.com/markusgattol",
    "followers_url": "https://api.github.com/users/markusgattol/followers",
    "following_url": "https://api.github.com/users/markusgattol/following{/other_user}",
    "gists_url": "https://api.github.com/users/markusgattol/gists{/gist_id}",
    "starred_url": "https://api.github.com/users/markusgattol/starred{/owner}{/repo}",
    "subscriptions_url": "https://api.github.com/users/markusgattol/subscriptions",
    "organizations_url": "https://api.github.com/users/markusgattol/orgs",
    "repos_url": "https://api.github.com/users/markusgattol/repos",
    "events_url": "https://api.github.com/users/markusgattol/events{/privacy}",
    "received_events_url": "https://api.github.com/users/markusgattol/received_events",
    "type": "User",
    "site_admin": false,
    "contributions": 53
  }
]
